{
  "beta_mwidth_non_parametric": "mwidth",
  "sig_peak_NS_EOS": "sig_peak_NS",
  "mu_cos_tilt_EOS": "mu_costilt",
  "mu_peakNS": "mu_peak_NS",
  "gamma_high": "gamma_high",
  "gamma_low_debug": "gamma_low",
  "wide_sig_chi_amax": "a_max",
  "gamma_low": "gamma_low",
  "mu_cos_tilt_non_parametric": "mu_costilt",
  "beta_low_non_parametric": "beta_1",
  "beta_low_NS_EOS": "beta_1",
  "mu_peakNS_non_parametric": "mu_peak_NS",
  "sigma_chi": "sig_chi1",
  "beta_low_NS_non_parametric": "beta_1",
  "gamma_low_non_parametric": "gamma_low",
  "gamma_low_debug_PEtest": "gamma_low",
  "mu_cos_tilt": "mu_costilt",
  "mu_cos_tilt_debug": "mu_costilt",
  "beta_mwidth": "mwidth",
  "gamma_low_PDB_multiPDB_non_parametric": "gamma_low",
  "gamma_low_EOS": "gamma_low",
  "sig_cos_tilt_EOS": "sig_costilt",
  "sig_peak_NS": "sig_peak_NS",
  "beta_low_EOS": "beta_1",
  "wide_sig_chi_amax_EOS": "a_max",
  "beta_low_NS": "beta_1",
  "sig_cos_tilt": "sig_costilt",
  "beta_high": "beta_2",
  "beta_low": "beta_1",
  "mu_peakNS_EOS": "mu_peak_NS",
  "gamma_high_EOS": "gamma_high",
  "gamma_low_EOS_PDB_multiPDB": "gamma_low",
  "gamma_low_EOS_PDB": "gamma_low",
  "m_spin_break": "m_spin_break",
  "sig_cos_tilt_non_parametric": "sig_costilt",
  "sig_peak_NS_non_parametric": "sig_peak_NS",
  "mu_chi1": "mu_chi1",
  "gamma_high_non_parametric": "gamma_high"
}